[
  {
    "title": "Information on enrollment as a Practical Project Student at TUM - TUM Global",
    "program_url": "https://www.international.tum.de/en/global/comingtotum/research-stays-for-students/practical-project-students/",
    "university": "Technical University of Munich",
    "country": "Germany",
    "degree_type": null,
    "deadline": null,
    "requirements": null,
    "description": null
  },
  {
    "title": "TUM - PhD Positions at the Munich Center for Machine Learning (MCML)",
    "program_url": "https://portal.mytum.de/jobs/wissenschaftler/NewsArticle_20241002_095812",
    "university": "Technical University of Munich",
    "country": "Germany",
    "degree_type": "PhD",
    "deadline": null,
    "requirements": null,
    "description": null
  },
  {
    "title": "Junior AI Engineer - Industrial Foundation Models (f/m/x)",
    "program_url": "https://www.bmwgroup.jobs/de/en/jobfinder/job-description-copy.173805.html",
    "university": "BMW Group",
    "country": "Germany",
    "degree_type": null,
    "deadline": null,
    "requirements": null,
    "description": null
  },
  {
    "title": "Scientific Assistant in Biomedical Machine Learning and Data Science",
    "program_url": "https://jobs.ethz.ch/job/view/JOPG_ethz_zYk0LUTJGSSeVBhMbV",
    "university": "ETH Zurich",
    "country": "Switzerland",
    "degree_type": null,
    "deadline": null,
    "requirements": null,
    "description": null
  },
  {
    "title": "Doctoral Positions in AI for Computational Thinking",
    "program_url": "https://jobs.ethz.ch/job/view/JOPG_ethz_OqnIo9oIOhdv38BDHq",
    "university": "ETH Zurich",
    "country": "Switzerland",
    "degree_type": "PhD",
    "deadline": null,
    "requirements": null,
    "description": null
  },
  {
    "title": "UZH: Doctoral Positions In Computational Visual Media Research (Prof. Dr. Jing Zeng)",
    "program_url": "https://jobs.uzh.ch/job-vacancies/doctoral-positions-in-computational-visual-media-research-prof-dr-jing-zeng/c1c6a704-c8f2-4344-ba89-f920453c8635",
    "university": "University of Zurich",
    "country": "Switzerland",
    "degree_type": "PhD",
    "deadline": null,
    "requirements": null,
    "description": null
  },
  {
    "title": "TUM - Wissenschaftliche/r Mitarbeiter/in – Strategische Forschungsentwicklung Robotik & KI (m/w/d)",
    "program_url": "https://portal.mytum.de/jobs/wissenschaftler/NewsArticle_20251117_142353",
    "university": "Technical University of Munich",
    "country": "Germany",
    "degree_type": null,
    "deadline": null,
    "requirements": null,
    "description": null
  },
  {
    "title": "TUM - PhD in Computer Science – Institute for AI and Informatics in Medicine (AIIM)",
    "program_url": "https://portal.mytum.de/jobs/wissenschaftler/NewsArticle_20251102_233202",
    "university": "Technical University of Munich",
    "country": "Germany",
    "degree_type": "PhD",
    "deadline": null,
    "requirements": null,
    "description": null
  },
  {
    "title": "TUM - Research Associate – AI at Work (m/f/d), Chair of Business Administration",
    "program_url": "https://portal.mytum.de/jobs/wissenschaftler/NewsArticle_20251126_120838",
    "university": "Technical University of Munich",
    "country": "Germany",
    "degree_type": "Research Position",
    "deadline": null,
    "requirements": null,
    "description": null
  },
  {
    "title": "fa.mgt.tum.de/fileadmin/w00chf/cm/Jobs/251120_Stellenausschreibung_WissMa.pdf#page=2.12",
    "program_url": "https://www.fa.mgt.tum.de/fileadmin/w00chf/cm/Jobs/251120_Stellenausschreibung_WissMa.pdf#page=2.12",
    "university": "Technical University of Munich",
    "country": "Germany",
    "degree_type": null,
    "deadline": null,
    "requirements": null,
    "description": null
  },
  {
    "title": "Doctoral INPhINIT fellowships Incoming - \"la Caixa\" Foundation",
    "program_url": "https://lacaixafoundation.org/en/doctoral-inphinit-fellowships-incoming-call",
    "university": "La Caixa Foundation",
    "country": null,
    "degree_type": "PhD",
    "deadline": null,
    "requirements": null,
    "description": null
  },
  {
    "title": "Open positions ‒ DHLAB ‐ EPFL",
    "program_url": "https://www.epfl.ch/labs/dhlab/openpositions/",
    "university": "EPFL",
    "country": "Switzerland",
    "degree_type": null,
    "deadline": null,
    "requirements": null,
    "description": null
  },
  {
    "title": "University of Zurich - PhD Data Science",
    "program_url": "https://dm3l.uzh.ch/en/studies/phdds",
    "university": "University of Zurich",
    "country": "Switzerland",
    "degree_type": "PhD",
    "deadline": null,
    "requirements": null,
    "description": null
  },
  {
    "title": "Home - TUM Visual Computing Application System",
    "program_url": "https://application.vc.in.tum.de/",
    "university": "Technical University of Munich",
    "country": "Germany",
    "degree_type": null,
    "deadline": null,
    "requirements": null,
    "description": null
  },
  {
    "title": "Home - Software Engineering for Business Information Systems",
    "program_url": "https://www.cs.cit.tum.de/sebis/home/",
    "university": "Technical University of Munich",
    "country": "Germany",
    "degree_type": null,
    "deadline": null,
    "requirements": null,
    "description": null
  },
  {
    "title": "Scholarship Positions | The World’s #1 Scholarship Website",
    "program_url": "https://scholarship-positions.com/",
    "university": "Scholarship Portal",
    "country": null,
    "degree_type": "Fellowship/Scholarship",
    "deadline": null,
    "requirements": null,
    "description": null
  },
  {
    "title": "Təqaüd Proqramları Archives - EduOnline.Az",
    "program_url": "https://eduonline.az/category/t%c9%99qaud-proqramlari/",
    "university": null,
    "country": null,
    "degree_type": "Fellowship/Scholarship",
    "deadline": null,
    "requirements": null,
    "description": null
  },
  {
    "title": "Alumni associations - DAAD",
    "program_url": "https://www.daad.de/en/alumni/alumni-associations/",
    "university": "DAAD",
    "country": null,
    "degree_type": null,
    "deadline": null,
    "requirements": null,
    "description": null
  },
  {
    "title": "Master of Science in Bioinformatics",
    "program_url": "https://www2.daad.de/deutschland/studienangebote/international-programmes/en/detail/4724/#tab_registration",
    "university": "DAAD",
    "country": "Germany",
    "degree_type": "Master",
    "deadline": null,
    "requirements": null,
    "description": null
  },
  {
    "title": "NAVi Technologies",
    "program_url": "https://endeavour.unimelb.edu.au/success-stories/navi-technologies",
    "university": "University of Melbourne",
    "country": null,
    "degree_type": null,
    "deadline": null,
    "requirements": null,
    "description": null
  },
  {
    "title": "Biomedical engineering startup Stelect wins Medtech’s Got Talent",
    "program_url": "https://eng.unimelb.edu.au/ingenium/graduate-stories/biomedical-engineering-startup-stelect-wins-medtechs-got-talent",
    "university": "University of Melbourne",
    "country": null,
    "degree_type": null,
    "deadline": null,
    "requirements": null,
    "description": null
  },
  {
    "title": "Medicine - International Programmes in Germany - DAAD",
    "program_url": "https://www2.daad.de/deutschland/studienangebote/international-programmes/en/detail/4590/#tab_registration",
    "university": "DAAD",
    "country": "Germany",
    "degree_type": "Internship",
    "deadline": null,
    "requirements": null,
    "description": null
  },
  {
    "title": "The Center for Brains, Minds & Machines",
    "program_url": "https://cbmm.mit.edu/education/courses",
    "university": "Massachusetts Institute of Technology",
    "country": "USA",
    "degree_type": null,
    "deadline": null,
    "requirements": null,
    "description": null
  },
  {
    "title": "Research - Donders Institute",
    "program_url": "https://www.ru.nl/donders/research/",
    "university": "Radboud University",
    "country": null,
    "degree_type": "Research Position",
    "deadline": null,
    "requirements": null,
    "description": null
  },
  {
    "title": "ERASMUSINTERN |",
    "program_url": "https://erasmusintern.org/",
    "university": "Erasmus Intern",
    "country": null,
    "degree_type": "Internship",
    "deadline": null,
    "requirements": null,
    "description": null
  },
  {
    "title": "Internships Search | ERASMUSINTERN",
    "program_url": "https://erasmusintern.org/traineeships?search_api_views_fulltext=neuroscience&field_traineeship_full_location_field_traineeship_location_count=All",
    "university": "Erasmus Intern",
    "country": null,
    "degree_type": "Internship",
    "deadline": null,
    "requirements": null,
    "description": null
  },
  {
    "title": "Azərbaycan üçün DAAD təqaüdləri | DAAD Azərbaycan",
    "program_url": "https://www.daad.az/az/teqaud-axtarisi/azerbaycan-uchun-daad-teqaudleri/",
    "university": "DAAD",
    "country": null,
    "degree_type": "Fellowship/Scholarship",
    "deadline": null,
    "requirements": null,
    "description": null
  },
  {
    "title": "Almanyada yüksek lisans, Almanyada yüksek lisans başvuruları",
    "program_url": "https://www.unialmanya.com/yuksek-lisans/",
    "university": null,
    "country": null,
    "degree_type": "Master",
    "deadline": null,
    "requirements": null,
    "description": null
  },
  {
    "title": "UTRIP - School of Science, the University of Tokyo",
    "program_url": "https://www.s.u-tokyo.ac.jp/en/utrip/index.html",
    "university": "University of Tokyo",
    "country": "Japan",
    "degree_type": null,
    "deadline": null,
    "requirements": null,
    "description": null
  },
  {
    "title": "Admission - PNC",
    "program_url": "https://pnc.unipd.it/phd-neuroscience/admission/",
    "university": "University of Padua",
    "country": "Italy",
    "degree_type": null,
    "deadline": null,
    "requirements": null,
    "description": null
  },
  {
    "title": "cis.lmu.de/web/arposition2026.html",
    "program_url": "https://cis.lmu.de/web/arposition2026.html",
    "university": "Ludwig Maximilian University of Munich",
    "country": "Germany",
    "degree_type": null,
    "deadline": null,
    "requirements": null,
    "description": null
  },
  {
    "title": "Research Scientist – Doctoral Candidate | EURAXESS",
    "program_url": "https://euraxess.ec.europa.eu/jobs/365834",
    "university": "EURAXESS",
    "country": null,
    "degree_type": "PhD",
    "deadline": null,
    "requirements": null,
    "description": null
  },
  {
    "title": "Software engineer position for Scientific AI Job Details | EPFL",
    "program_url": "https://careers.epfl.ch/job/Gen%C3%A8ve-Software-engineer-position-for-Scientific-AI/940652874/",
    "university": "EPFL",
    "country": "Switzerland",
    "degree_type": null,
    "deadline": null,
    "requirements": null,
    "description": null
  },
  {
    "title": "Home - Social Data Science and AI Lab - LMU München",
    "program_url": "https://www.stat.lmu.de/soda/en/",
    "university": "Ludwig Maximilian University of Munich",
    "country": "Germany",
    "degree_type": null,
    "deadline": null,
    "requirements": null,
    "description": null
  }
]